redistock/__init__.py
redistock/redistock.py
redistock-0.1.3.dist-info/LICENSE
redistock-0.1.3.dist-info/METADATA
redistock-0.1.3.dist-info/WHEEL
redistock-0.1.3.dist-info/top_level.txt
redistock-0.1.3.dist-info/RECORD
